{
  "metadata": {
    "name": "Iot (Growth, eu-west-1)",
    "id": "c9949c52",
    "pattern": "iot",
    "complexity": "xlarge",
    "region": "eu-west-1",
    "region_name": "EU (Ireland)",
    "cost_tier": "growth",
    "cost_tier_label": "Growth",
    "total_services": 32,
    "total_dependencies": 65,
    "total_cost_monthly": 12520.61,
    "generated_at": "2026-03-01T19:23:58.093262",
    "variation_seed": 32840
  },
  "services": [
    {
      "id": "device-mgr-iot-000",
      "name": "device-mgr-iot",
      "type": "service",
      "aws_service": "AWS IoT Core",
      "cost_monthly": 728.6,
      "owner": "analytics-team",
      "environment": "production",
      "region": "eu-west-1",
      "attributes": {
        "instance_type": "t3.medium",
        "auto_scaling": false,
        "multi_az": true,
        "encryption": true
      }
    },
    {
      "id": "digital-twin-kinesis-001",
      "name": "digital-twin-kinesis",
      "type": "queue",
      "aws_service": "Amazon Kinesis",
      "cost_monthly": 199.0,
      "owner": "content-team",
      "environment": "production",
      "region": "eu-west-1",
      "attributes": {
        "instance_type": "m5.large",
        "auto_scaling": true,
        "multi_az": false,
        "encryption": true
      }
    },
    {
      "id": "digital-twin-lambda-002",
      "name": "digital-twin-lambda",
      "type": "serverless",
      "aws_service": "AWS Lambda",
      "cost_monthly": 250.78,
      "owner": "billing-team",
      "environment": "production",
      "region": "eu-west-1",
      "attributes": {
        "instance_type": "t3.micro",
        "auto_scaling": false,
        "multi_az": true,
        "encryption": true
      }
    },
    {
      "id": "rules-engine-dynamodb-003",
      "name": "rules-engine-dynamodb",
      "type": "database",
      "aws_service": "Amazon DynamoDB",
      "cost_monthly": 236.31,
      "owner": "devops",
      "environment": "production",
      "region": "eu-west-1",
      "attributes": {
        "instance_type": "m5.large",
        "auto_scaling": true,
        "multi_az": false,
        "encryption": true
      }
    },
    {
      "id": "device-mgr-s3-004",
      "name": "device-mgr-s3",
      "type": "storage",
      "aws_service": "Amazon S3",
      "cost_monthly": 1023.25,
      "owner": "backend-squad",
      "environment": "production",
      "region": "eu-west-1",
      "attributes": {
        "instance_type": "t3.micro",
        "auto_scaling": false,
        "multi_az": true,
        "encryption": true
      }
    },
    {
      "id": "edge-telemetry-005",
      "name": "edge-telemetry",
      "type": "serverless",
      "aws_service": "AWS Step Functions",
      "cost_monthly": 80.68,
      "owner": "data-eng",
      "environment": "staging",
      "region": "eu-west-1",
      "attributes": {
        "instance_type": "c5.large",
        "auto_scaling": false,
        "multi_az": false,
        "encryption": true
      }
    },
    {
      "id": "central-fleet-006",
      "name": "central-fleet",
      "type": "serverless",
      "aws_service": "Amazon EventBridge",
      "cost_monthly": 106.87,
      "owner": "infra-core",
      "environment": "dr",
      "region": "eu-west-1",
      "attributes": {
        "instance_type": "c5.large",
        "auto_scaling": false,
        "multi_az": true,
        "encryption": true
      }
    },
    {
      "id": "internal-alerts-007",
      "name": "internal-alerts",
      "type": "service",
      "aws_service": "Amazon CloudWatch",
      "cost_monthly": 534.89,
      "owner": "identity-team",
      "environment": "production",
      "region": "eu-west-1",
      "attributes": {
        "instance_type": "t3.large",
        "auto_scaling": false,
        "multi_az": true,
        "encryption": false
      }
    },
    {
      "id": "async-commands-008",
      "name": "async-commands",
      "type": "search",
      "aws_service": "Amazon OpenSearch",
      "cost_monthly": 351.31,
      "owner": "infra-core",
      "environment": "production",
      "region": "eu-west-1",
      "attributes": {
        "instance_type": "c5.large",
        "auto_scaling": true,
        "multi_az": false,
        "encryption": true
      }
    },
    {
      "id": "private-device-mgr-009",
      "name": "private-device-mgr",
      "type": "batch",
      "aws_service": "Amazon EC2 (Worker)",
      "cost_monthly": 220.66,
      "owner": "billing-team",
      "environment": "production",
      "region": "eu-west-1",
      "attributes": {
        "instance_type": "c5.large",
        "auto_scaling": true,
        "multi_az": false,
        "encryption": true
      }
    },
    {
      "id": "async-digital-twin-010",
      "name": "async-digital-twin",
      "type": "queue",
      "aws_service": "Amazon SQS",
      "cost_monthly": 44.26,
      "owner": "api-gateway-team",
      "environment": "production",
      "region": "eu-west-1",
      "attributes": {
        "instance_type": "m5.xlarge",
        "auto_scaling": false,
        "multi_az": false,
        "encryption": true
      }
    },
    {
      "id": "primary-digital-twin-011",
      "name": "primary-digital-twin",
      "type": "queue",
      "aws_service": "Amazon SNS",
      "cost_monthly": 92.96,
      "owner": "backend-squad",
      "environment": "production",
      "region": "eu-west-1",
      "attributes": {
        "instance_type": "t3.large",
        "auto_scaling": true,
        "multi_az": true,
        "encryption": true
      }
    },
    {
      "id": "core-commands-012",
      "name": "core-commands",
      "type": "batch",
      "aws_service": "AWS Glue",
      "cost_monthly": 800.49,
      "owner": "devops",
      "environment": "production",
      "region": "eu-west-1",
      "attributes": {
        "instance_type": "c5.large",
        "auto_scaling": false,
        "multi_az": false,
        "encryption": true
      }
    },
    {
      "id": "realtime-rules-engine-013",
      "name": "realtime-rules-engine",
      "type": "database",
      "aws_service": "Amazon RDS PostgreSQL",
      "cost_monthly": 939.48,
      "owner": "analytics-team",
      "environment": "production",
      "region": "eu-west-1",
      "attributes": {
        "instance_type": "m5.xlarge",
        "auto_scaling": false,
        "multi_az": true,
        "encryption": true
      }
    },
    {
      "id": "batch-commands-014",
      "name": "batch-commands",
      "type": "batch",
      "aws_service": "Amazon EMR",
      "cost_monthly": 510.38,
      "owner": "notifications",
      "environment": "production",
      "region": "eu-west-1",
      "attributes": {
        "instance_type": "t3.small",
        "auto_scaling": true,
        "multi_az": false,
        "encryption": true
      }
    },
    {
      "id": "global-shadow-015",
      "name": "global-shadow",
      "type": "queue",
      "aws_service": "Amazon SNS",
      "cost_monthly": 40.02,
      "owner": "growth-eng",
      "environment": "production",
      "region": "eu-west-1",
      "attributes": {
        "instance_type": "m5.large",
        "auto_scaling": false,
        "multi_az": true,
        "encryption": false
      }
    },
    {
      "id": "edge-alerts-016",
      "name": "edge-alerts",
      "type": "batch",
      "aws_service": "AWS Elemental MediaConvert",
      "cost_monthly": 490.88,
      "owner": "ml-ops",
      "environment": "staging",
      "region": "eu-west-1",
      "attributes": {
        "instance_type": "t3.large",
        "auto_scaling": false,
        "multi_az": true,
        "encryption": false
      }
    },
    {
      "id": "public-fleet-017",
      "name": "public-fleet",
      "type": "search",
      "aws_service": "Amazon OpenSearch",
      "cost_monthly": 813.12,
      "owner": "data-eng",
      "environment": "production",
      "region": "eu-west-1",
      "attributes": {
        "instance_type": "m5.large",
        "auto_scaling": false,
        "multi_az": true,
        "encryption": false
      }
    },
    {
      "id": "shared-telemetry-018",
      "name": "shared-telemetry",
      "type": "queue",
      "aws_service": "Amazon SNS",
      "cost_monthly": 43.79,
      "owner": "notifications",
      "environment": "dr",
      "region": "eu-west-1",
      "attributes": {
        "instance_type": "m5.xlarge",
        "auto_scaling": false,
        "multi_az": false,
        "encryption": true
      }
    },
    {
      "id": "shared-alerts-019",
      "name": "shared-alerts",
      "type": "batch",
      "aws_service": "AWS Glue",
      "cost_monthly": 209.08,
      "owner": "security",
      "environment": "production",
      "region": "eu-west-1",
      "attributes": {
        "instance_type": "t3.small",
        "auto_scaling": true,
        "multi_az": false,
        "encryption": false
      }
    },
    {
      "id": "main-device-mgr-020",
      "name": "main-device-mgr",
      "type": "database",
      "aws_service": "Amazon RDS MySQL",
      "cost_monthly": 1014.74,
      "owner": "infra-core",
      "environment": "dr",
      "region": "eu-west-1",
      "attributes": {
        "instance_type": "m5.large",
        "auto_scaling": true,
        "multi_az": false,
        "encryption": false
      }
    },
    {
      "id": "public-fleet-021",
      "name": "public-fleet",
      "type": "cdn",
      "aws_service": "Amazon CloudFront",
      "cost_monthly": 127.77,
      "owner": "security",
      "environment": "production",
      "region": "eu-west-1",
      "attributes": {
        "instance_type": "r5.large",
        "auto_scaling": false,
        "multi_az": false,
        "encryption": true
      }
    },
    {
      "id": "public-provisioning-022",
      "name": "public-provisioning",
      "type": "cache",
      "aws_service": "Amazon ElastiCache Redis",
      "cost_monthly": 412.66,
      "owner": "frontend-guild",
      "environment": "production",
      "region": "eu-west-1",
      "attributes": {
        "instance_type": "t3.micro",
        "auto_scaling": true,
        "multi_az": true,
        "encryption": true
      }
    },
    {
      "id": "backup-commands-023",
      "name": "backup-commands",
      "type": "search",
      "aws_service": "Amazon OpenSearch",
      "cost_monthly": 386.09,
      "owner": "api-gateway-team",
      "environment": "production",
      "region": "eu-west-1",
      "attributes": {
        "instance_type": "t3.small",
        "auto_scaling": true,
        "multi_az": false,
        "encryption": true
      }
    },
    {
      "id": "central-fleet-024",
      "name": "central-fleet",
      "type": "storage",
      "aws_service": "Amazon EFS",
      "cost_monthly": 175.99,
      "owner": "data-eng",
      "environment": "dr",
      "region": "eu-west-1",
      "attributes": {
        "instance_type": "m5.large",
        "auto_scaling": true,
        "multi_az": true,
        "encryption": true
      }
    },
    {
      "id": "public-provisioning-025",
      "name": "public-provisioning",
      "type": "batch",
      "aws_service": "Amazon EC2 (Worker)",
      "cost_monthly": 359.83,
      "owner": "search-team",
      "environment": "staging",
      "region": "eu-west-1",
      "attributes": {
        "instance_type": "m5.large",
        "auto_scaling": false,
        "multi_az": true,
        "encryption": true
      }
    },
    {
      "id": "secondary-firmware-026",
      "name": "secondary-firmware",
      "type": "storage",
      "aws_service": "Amazon S3",
      "cost_monthly": 191.16,
      "owner": "content-team",
      "environment": "staging",
      "region": "eu-west-1",
      "attributes": {
        "instance_type": "t3.small",
        "auto_scaling": false,
        "multi_az": true,
        "encryption": true
      }
    },
    {
      "id": "primary-fleet-027",
      "name": "primary-fleet",
      "type": "service",
      "aws_service": "AWS Secrets Manager",
      "cost_monthly": 21.18,
      "owner": "platform-team",
      "environment": "production",
      "region": "eu-west-1",
      "attributes": {
        "instance_type": "c5.large",
        "auto_scaling": false,
        "multi_az": false,
        "encryption": false
      }
    },
    {
      "id": "staging-firmware-028",
      "name": "staging-firmware",
      "type": "search",
      "aws_service": "Amazon OpenSearch",
      "cost_monthly": 543.05,
      "owner": "payments",
      "environment": "production",
      "region": "eu-west-1",
      "attributes": {
        "instance_type": "m5.xlarge",
        "auto_scaling": true,
        "multi_az": true,
        "encryption": true
      }
    },
    {
      "id": "public-provisioning-029",
      "name": "public-provisioning",
      "type": "batch",
      "aws_service": "Amazon EMR",
      "cost_monthly": 784.94,
      "owner": "notifications",
      "environment": "production",
      "region": "eu-west-1",
      "attributes": {
        "instance_type": "c5.large",
        "auto_scaling": false,
        "multi_az": false,
        "encryption": true
      }
    },
    {
      "id": "central-fleet-030",
      "name": "central-fleet",
      "type": "database",
      "aws_service": "Amazon RDS PostgreSQL",
      "cost_monthly": 603.6,
      "owner": "infra-core",
      "environment": "production",
      "region": "eu-west-1",
      "attributes": {
        "instance_type": "r5.large",
        "auto_scaling": false,
        "multi_az": true,
        "encryption": true
      }
    },
    {
      "id": "staging-commands-031",
      "name": "staging-commands",
      "type": "service",
      "aws_service": "Amazon CloudWatch",
      "cost_monthly": 182.79,
      "owner": "platform-team",
      "environment": "staging",
      "region": "eu-west-1",
      "attributes": {
        "instance_type": "t3.small",
        "auto_scaling": false,
        "multi_az": false,
        "encryption": true
      }
    }
  ],
  "dependencies": [
    {
      "source": "device-mgr-iot-000",
      "target": "digital-twin-kinesis-001",
      "type": "writes",
      "weight": 0.66
    },
    {
      "source": "digital-twin-kinesis-001",
      "target": "digital-twin-lambda-002",
      "type": "subscribes",
      "weight": 0.45
    },
    {
      "source": "digital-twin-lambda-002",
      "target": "rules-engine-dynamodb-003",
      "type": "subscribes",
      "weight": 0.79
    },
    {
      "source": "rules-engine-dynamodb-003",
      "target": "device-mgr-s3-004",
      "type": "caches",
      "weight": 0.69
    },
    {
      "source": "device-mgr-s3-004",
      "target": "edge-telemetry-005",
      "type": "caches",
      "weight": 0.7
    },
    {
      "source": "edge-telemetry-005",
      "target": "central-fleet-006",
      "type": "subscribes",
      "weight": 0.76
    },
    {
      "source": "central-fleet-006",
      "target": "internal-alerts-007",
      "type": "queries",
      "weight": 0.82
    },
    {
      "source": "internal-alerts-007",
      "target": "async-commands-008",
      "type": "subscribes",
      "weight": 0.44
    },
    {
      "source": "async-commands-008",
      "target": "private-device-mgr-009",
      "type": "calls",
      "weight": 0.37
    },
    {
      "source": "private-device-mgr-009",
      "target": "async-digital-twin-010",
      "type": "calls",
      "weight": 0.33
    },
    {
      "source": "async-digital-twin-010",
      "target": "primary-digital-twin-011",
      "type": "triggers",
      "weight": 0.43
    },
    {
      "source": "primary-digital-twin-011",
      "target": "core-commands-012",
      "type": "queries",
      "weight": 0.78
    },
    {
      "source": "core-commands-012",
      "target": "realtime-rules-engine-013",
      "type": "writes",
      "weight": 0.78
    },
    {
      "source": "realtime-rules-engine-013",
      "target": "batch-commands-014",
      "type": "subscribes",
      "weight": 0.99
    },
    {
      "source": "batch-commands-014",
      "target": "global-shadow-015",
      "type": "caches",
      "weight": 0.69
    },
    {
      "source": "global-shadow-015",
      "target": "edge-alerts-016",
      "type": "reads",
      "weight": 0.62
    },
    {
      "source": "edge-alerts-016",
      "target": "public-fleet-017",
      "type": "caches",
      "weight": 0.86
    },
    {
      "source": "public-fleet-017",
      "target": "shared-telemetry-018",
      "type": "subscribes",
      "weight": 0.86
    },
    {
      "source": "shared-telemetry-018",
      "target": "shared-alerts-019",
      "type": "reads",
      "weight": 0.84
    },
    {
      "source": "shared-alerts-019",
      "target": "main-device-mgr-020",
      "type": "writes",
      "weight": 0.81
    },
    {
      "source": "main-device-mgr-020",
      "target": "public-fleet-021",
      "type": "triggers",
      "weight": 0.48
    },
    {
      "source": "public-fleet-021",
      "target": "public-provisioning-022",
      "type": "triggers",
      "weight": 0.83
    },
    {
      "source": "public-provisioning-022",
      "target": "backup-commands-023",
      "type": "subscribes",
      "weight": 0.62
    },
    {
      "source": "backup-commands-023",
      "target": "central-fleet-024",
      "type": "calls",
      "weight": 0.5
    },
    {
      "source": "central-fleet-024",
      "target": "public-provisioning-025",
      "type": "queries",
      "weight": 0.88
    },
    {
      "source": "public-provisioning-025",
      "target": "secondary-firmware-026",
      "type": "calls",
      "weight": 0.81
    },
    {
      "source": "secondary-firmware-026",
      "target": "primary-fleet-027",
      "type": "writes",
      "weight": 0.86
    },
    {
      "source": "primary-fleet-027",
      "target": "staging-firmware-028",
      "type": "caches",
      "weight": 0.8
    },
    {
      "source": "staging-firmware-028",
      "target": "public-provisioning-029",
      "type": "subscribes",
      "weight": 0.45
    },
    {
      "source": "public-provisioning-029",
      "target": "central-fleet-030",
      "type": "triggers",
      "weight": 0.63
    },
    {
      "source": "central-fleet-030",
      "target": "staging-commands-031",
      "type": "calls",
      "weight": 0.81
    },
    {
      "source": "digital-twin-lambda-002",
      "target": "main-device-mgr-020",
      "type": "triggers",
      "weight": 0.89
    },
    {
      "source": "core-commands-012",
      "target": "digital-twin-kinesis-001",
      "type": "calls",
      "weight": 0.47
    },
    {
      "source": "edge-alerts-016",
      "target": "async-commands-008",
      "type": "writes",
      "weight": 0.57
    },
    {
      "source": "shared-telemetry-018",
      "target": "staging-commands-031",
      "type": "caches",
      "weight": 0.98
    },
    {
      "source": "async-digital-twin-010",
      "target": "async-commands-008",
      "type": "calls",
      "weight": 0.38
    },
    {
      "source": "shared-telemetry-018",
      "target": "public-fleet-017",
      "type": "subscribes",
      "weight": 0.57
    },
    {
      "source": "backup-commands-023",
      "target": "digital-twin-kinesis-001",
      "type": "calls",
      "weight": 0.66
    },
    {
      "source": "public-provisioning-029",
      "target": "primary-fleet-027",
      "type": "writes",
      "weight": 0.79
    },
    {
      "source": "shared-alerts-019",
      "target": "edge-alerts-016",
      "type": "writes",
      "weight": 0.71
    },
    {
      "source": "async-commands-008",
      "target": "backup-commands-023",
      "type": "caches",
      "weight": 0.29
    },
    {
      "source": "shared-telemetry-018",
      "target": "async-commands-008",
      "type": "reads",
      "weight": 0.21
    },
    {
      "source": "async-commands-008",
      "target": "device-mgr-s3-004",
      "type": "calls",
      "weight": 0.65
    },
    {
      "source": "device-mgr-s3-004",
      "target": "public-provisioning-025",
      "type": "reads",
      "weight": 0.79
    },
    {
      "source": "staging-commands-031",
      "target": "public-provisioning-025",
      "type": "reads",
      "weight": 0.22
    },
    {
      "source": "shared-telemetry-018",
      "target": "backup-commands-023",
      "type": "caches",
      "weight": 0.19
    },
    {
      "source": "public-fleet-021",
      "target": "device-mgr-s3-004",
      "type": "caches",
      "weight": 0.91
    },
    {
      "source": "public-fleet-021",
      "target": "backup-commands-023",
      "type": "subscribes",
      "weight": 0.75
    },
    {
      "source": "main-device-mgr-020",
      "target": "edge-alerts-016",
      "type": "reads",
      "weight": 0.53
    },
    {
      "source": "public-provisioning-022",
      "target": "digital-twin-kinesis-001",
      "type": "subscribes",
      "weight": 0.5
    },
    {
      "source": "central-fleet-024",
      "target": "primary-fleet-027",
      "type": "queries",
      "weight": 0.54
    },
    {
      "source": "private-device-mgr-009",
      "target": "backup-commands-023",
      "type": "calls",
      "weight": 0.25
    },
    {
      "source": "device-mgr-s3-004",
      "target": "device-mgr-iot-000",
      "type": "triggers",
      "weight": 0.94
    },
    {
      "source": "async-digital-twin-010",
      "target": "device-mgr-iot-000",
      "type": "writes",
      "weight": 0.2
    },
    {
      "source": "primary-fleet-027",
      "target": "backup-commands-023",
      "type": "caches",
      "weight": 0.19
    },
    {
      "source": "async-digital-twin-010",
      "target": "digital-twin-lambda-002",
      "type": "reads",
      "weight": 0.26
    },
    {
      "source": "digital-twin-lambda-002",
      "target": "edge-alerts-016",
      "type": "triggers",
      "weight": 0.56
    },
    {
      "source": "public-provisioning-029",
      "target": "shared-telemetry-018",
      "type": "caches",
      "weight": 0.81
    },
    {
      "source": "central-fleet-006",
      "target": "staging-firmware-028",
      "type": "calls",
      "weight": 0.42
    },
    {
      "source": "core-commands-012",
      "target": "shared-telemetry-018",
      "type": "triggers",
      "weight": 0.96
    },
    {
      "source": "edge-telemetry-005",
      "target": "shared-alerts-019",
      "type": "queries",
      "weight": 0.74
    },
    {
      "source": "private-device-mgr-009",
      "target": "batch-commands-014",
      "type": "triggers",
      "weight": 0.11
    },
    {
      "source": "primary-fleet-027",
      "target": "internal-alerts-007",
      "type": "writes",
      "weight": 0.31
    },
    {
      "source": "edge-telemetry-005",
      "target": "digital-twin-lambda-002",
      "type": "queries",
      "weight": 0.44
    },
    {
      "source": "batch-commands-014",
      "target": "realtime-rules-engine-013",
      "type": "queries",
      "weight": 0.17
    }
  ]
}