{"nodes": [{"id": "digital-twin-iot-000", "name": "digital-twin-iot", "type": "service", "owner": "infra-core", "cost_monthly": 199.48, "cost_share": 4.96, "environment": "dr", "attributes": {"instance_type": "t3.small", "auto_scaling": true, "multi_az": true, "encryption": false}, "color": "#6366f1", "degree_centrality": 0.2174, "betweenness_centrality": 0.0573, "in_degree": 1, "out_degree": 4, "val": 10.522}, {"id": "shadow-kinesis-001", "name": "shadow-kinesis", "type": "queue", "owner": "notifications", "cost_monthly": 97.8, "cost_share": 2.43, "environment": "production", "attributes": {"instance_type": "r5.large", "auto_scaling": false, "multi_az": false, "encryption": true}, "color": "#ec4899", "degree_centrality": 0.2609, "betweenness_centrality": 0.164, "in_degree": 4, "out_degree": 2, "val": 11.827000000000002}, {"id": "provisioning-lambda-002", "name": "provisioning-lambda", "type": "serverless", "owner": "security", "cost_monthly": 252.45, "cost_share": 6.28, "environment": "dr", "attributes": {"instance_type": "c5.large", "auto_scaling": true, "multi_az": false, "encryption": true}, "color": "#8b5cf6", "degree_centrality": 0.2174, "betweenness_centrality": 0.1917, "in_degree": 3, "out_degree": 2, "val": 10.522}, {"id": "firmware-dynamodb-003", "name": "firmware-dynamodb", "type": "database", "owner": "data-eng", "cost_monthly": 182.85, "cost_share": 4.55, "environment": "production", "attributes": {"instance_type": "t3.large", "auto_scaling": true, "multi_az": false, "encryption": true}, "color": "#10b981", "degree_centrality": 0.1304, "betweenness_centrality": 0.0672, "in_degree": 2, "out_degree": 1, "val": 7.911999999999999}, {"id": "commands-s3-004", "name": "commands-s3", "type": "storage", "owner": "reliability-eng", "cost_monthly": 111.86, "cost_share": 2.78, "environment": "production", "attributes": {"instance_type": "t3.small", "auto_scaling": true, "multi_az": false, "encryption": true}, "color": "#3b82f6", "degree_centrality": 0.1739, "betweenness_centrality": 0.0672, "in_degree": 1, "out_degree": 3, "val": 9.216999999999999}, {"id": "backup-digital-twin-005", "name": "backup-digital-twin", "type": "batch", "owner": "billing-team", "cost_monthly": 182.67, "cost_share": 4.54, "environment": "dr", "attributes": {"instance_type": "m5.large", "auto_scaling": true, "multi_az": true, "encryption": true}, "color": "#84cc16", "degree_centrality": 0.1739, "betweenness_centrality": 0.0336, "in_degree": 2, "out_degree": 2, "val": 9.216999999999999}, {"id": "core-firmware-006", "name": "core-firmware", "type": "queue", "owner": "reliability-eng", "cost_monthly": 43.14, "cost_share": 1.07, "environment": "production", "attributes": {"instance_type": "r5.large", "auto_scaling": false, "multi_az": true, "encryption": true}, "color": "#ec4899", "degree_centrality": 0.2609, "betweenness_centrality": 0.2767, "in_degree": 5, "out_degree": 1, "val": 11.827000000000002}, {"id": "cold-telemetry-007", "name": "cold-telemetry", "type": "serverless", "owner": "identity-team", "cost_monthly": 70.68, "cost_share": 1.76, "environment": "production", "attributes": {"instance_type": "c5.large", "auto_scaling": true, "multi_az": false, "encryption": true}, "color": "#8b5cf6", "degree_centrality": 0.1739, "betweenness_centrality": 0.2767, "in_degree": 1, "out_degree": 3, "val": 9.216999999999999}, {"id": "staging-commands-008", "name": "staging-commands", "type": "search", "owner": "frontend-guild", "cost_monthly": 308.05, "cost_share": 7.66, "environment": "production", "attributes": {"instance_type": "c5.large", "auto_scaling": false, "multi_az": false, "encryption": true}, "color": "#ef4444", "degree_centrality": 0.1304, "betweenness_centrality": 0.0138, "in_degree": 1, "out_degree": 2, "val": 7.911999999999999}, {"id": "batch-shadow-009", "name": "batch-shadow", "type": "batch", "owner": "frontend-guild", "cost_monthly": 136.38, "cost_share": 3.39, "environment": "dr", "attributes": {"instance_type": "m5.large", "auto_scaling": true, "multi_az": false, "encryption": true}, "color": "#84cc16", "degree_centrality": 0.1304, "betweenness_centrality": 0.0375, "in_degree": 2, "out_degree": 1, "val": 7.911999999999999}, {"id": "central-rules-engine-010", "name": "central-rules-engine", "type": "serverless", "owner": "ml-ops", "cost_monthly": 82.09, "cost_share": 2.04, "environment": "staging", "attributes": {"instance_type": "t3.large", "auto_scaling": false, "multi_az": false, "encryption": true}, "color": "#8b5cf6", "degree_centrality": 0.3043, "betweenness_centrality": 0.2767, "in_degree": 4, "out_degree": 3, "val": 13.129000000000001}, {"id": "global-telemetry-011", "name": "global-telemetry", "type": "queue", "owner": "data-eng", "cost_monthly": 16.02, "cost_share": 0.4, "environment": "production", "attributes": {"instance_type": "t3.small", "auto_scaling": true, "multi_az": false, "encryption": true}, "color": "#ec4899", "degree_centrality": 0.3043, "betweenness_centrality": 0.1561, "in_degree": 3, "out_degree": 4, "val": 13.129000000000001}, {"id": "cold-digital-twin-012", "name": "cold-digital-twin", "type": "service", "owner": "devops", "cost_monthly": 128.97, "cost_share": 3.21, "environment": "production", "attributes": {"instance_type": "t3.medium", "auto_scaling": true, "multi_az": true, "encryption": false}, "color": "#6366f1", "degree_centrality": 0.087, "betweenness_centrality": 0.0, "in_degree": 1, "out_degree": 1, "val": 6.609999999999999}, {"id": "primary-commands-013", "name": "primary-commands", "type": "batch", "owner": "backend-squad", "cost_monthly": 300.43, "cost_share": 7.47, "environment": "dr", "attributes": {"instance_type": "m5.xlarge", "auto_scaling": false, "multi_az": true, "encryption": true}, "color": "#84cc16", "degree_centrality": 0.2609, "betweenness_centrality": 0.1739, "in_degree": 4, "out_degree": 2, "val": 11.827000000000002}, {"id": "core-firmware-014", "name": "core-firmware", "type": "service", "owner": "search-team", "cost_monthly": 174.24, "cost_share": 4.33, "environment": "staging", "attributes": {"instance_type": "t3.medium", "auto_scaling": true, "multi_az": false, "encryption": true}, "color": "#6366f1", "degree_centrality": 0.1739, "betweenness_centrality": 0.081, "in_degree": 1, "out_degree": 3, "val": 9.216999999999999}, {"id": "hot-shadow-015", "name": "hot-shadow", "type": "database", "owner": "billing-team", "cost_monthly": 245.25, "cost_share": 6.1, "environment": "staging", "attributes": {"instance_type": "t3.micro", "auto_scaling": false, "multi_az": false, "encryption": true}, "color": "#10b981", "degree_centrality": 0.2174, "betweenness_centrality": 0.1206, "in_degree": 3, "out_degree": 2, "val": 10.522}, {"id": "edge-shadow-016", "name": "edge-shadow", "type": "queue", "owner": "analytics-team", "cost_monthly": 269.19, "cost_share": 6.69, "environment": "production", "attributes": {"instance_type": "m5.large", "auto_scaling": false, "multi_az": true, "encryption": true}, "color": "#ec4899", "degree_centrality": 0.2174, "betweenness_centrality": 0.168, "in_degree": 3, "out_degree": 2, "val": 10.522}, {"id": "realtime-fleet-017", "name": "realtime-fleet", "type": "queue", "owner": "identity-team", "cost_monthly": 193.02, "cost_share": 4.8, "environment": "production", "attributes": {"instance_type": "t3.medium", "auto_scaling": false, "multi_az": true, "encryption": true}, "color": "#ec4899", "degree_centrality": 0.1304, "betweenness_centrality": 0.0553, "in_degree": 2, "out_degree": 1, "val": 7.911999999999999}, {"id": "realtime-telemetry-018", "name": "realtime-telemetry", "type": "load_balancer", "owner": "content-team", "cost_monthly": 52.38, "cost_share": 1.3, "environment": "staging", "attributes": {"instance_type": "t3.micro", "auto_scaling": false, "multi_az": true, "encryption": true}, "color": "#14b8a6", "degree_centrality": 0.2174, "betweenness_centrality": 0.2213, "in_degree": 2, "out_degree": 3, "val": 10.522}, {"id": "main-commands-019", "name": "main-commands", "type": "database", "owner": "devops", "cost_monthly": 403.73, "cost_share": 10.04, "environment": "production", "attributes": {"instance_type": "c5.large", "auto_scaling": true, "multi_az": true, "encryption": true}, "color": "#10b981", "degree_centrality": 0.1739, "betweenness_centrality": 0.087, "in_degree": 1, "out_degree": 3, "val": 9.216999999999999}, {"id": "main-provisioning-020", "name": "main-provisioning", "type": "service", "owner": "infra-core", "cost_monthly": 19.05, "cost_share": 0.47, "environment": "staging", "attributes": {"instance_type": "t3.medium", "auto_scaling": false, "multi_az": false, "encryption": true}, "color": "#6366f1", "degree_centrality": 0.087, "betweenness_centrality": 0.0119, "in_degree": 1, "out_degree": 1, "val": 6.609999999999999}, {"id": "regional-firmware-021", "name": "regional-firmware", "type": "service", "owner": "payments", "cost_monthly": 200.84, "cost_share": 4.99, "environment": "staging", "attributes": {"instance_type": "c5.large", "auto_scaling": false, "multi_az": true, "encryption": false}, "color": "#6366f1", "degree_centrality": 0.1739, "betweenness_centrality": 0.0791, "in_degree": 2, "out_degree": 2, "val": 9.216999999999999}, {"id": "batch-rules-engine-022", "name": "batch-rules-engine", "type": "service", "owner": "platform-team", "cost_monthly": 312.67, "cost_share": 7.77, "environment": "production", "attributes": {"instance_type": "r5.large", "auto_scaling": false, "multi_az": false, "encryption": true}, "color": "#6366f1", "degree_centrality": 0.2174, "betweenness_centrality": 0.1858, "in_degree": 2, "out_degree": 3, "val": 10.522}, {"id": "central-firmware-023", "name": "central-firmware", "type": "serverless", "owner": "ml-ops", "cost_monthly": 38.46, "cost_share": 0.96, "environment": "production", "attributes": {"instance_type": "r5.large", "auto_scaling": true, "multi_az": true, "encryption": true}, "color": "#8b5cf6", "degree_centrality": 0.087, "betweenness_centrality": 0.0059, "in_degree": 1, "out_degree": 1, "val": 6.609999999999999}], "links": [{"source": "digital-twin-iot-000", "target": "shadow-kinesis-001", "type": "reads", "weight": 0.7}, {"source": "digital-twin-iot-000", "target": "core-firmware-006", "type": "triggers", "weight": 0.98}, {"source": "digital-twin-iot-000", "target": "edge-shadow-016", "type": "queries", "weight": 0.59}, {"source": "digital-twin-iot-000", "target": "firmware-dynamodb-003", "type": "triggers", "weight": 0.58}, {"source": "shadow-kinesis-001", "target": "provisioning-lambda-002", "type": "subscribes", "weight": 0.44}, {"source": "shadow-kinesis-001", "target": "global-telemetry-011", "type": "writes", "weight": 0.86}, {"source": "provisioning-lambda-002", "target": "firmware-dynamodb-003", "type": "queries", "weight": 0.95}, {"source": "provisioning-lambda-002", "target": "central-rules-engine-010", "type": "triggers", "weight": 0.17}, {"source": "firmware-dynamodb-003", "target": "commands-s3-004", "type": "caches", "weight": 0.74}, {"source": "commands-s3-004", "target": "backup-digital-twin-005", "type": "calls", "weight": 0.49}, {"source": "commands-s3-004", "target": "edge-shadow-016", "type": "reads", "weight": 0.58}, {"source": "commands-s3-004", "target": "primary-commands-013", "type": "triggers", "weight": 0.36}, {"source": "backup-digital-twin-005", "target": "core-firmware-006", "type": "caches", "weight": 0.72}, {"source": "backup-digital-twin-005", "target": "hot-shadow-015", "type": "calls", "weight": 0.14}, {"source": "core-firmware-006", "target": "cold-telemetry-007", "type": "subscribes", "weight": 0.41}, {"source": "cold-telemetry-007", "target": "staging-commands-008", "type": "triggers", "weight": 0.61}, {"source": "cold-telemetry-007", "target": "shadow-kinesis-001", "type": "reads", "weight": 0.31}, {"source": "cold-telemetry-007", "target": "realtime-telemetry-018", "type": "reads", "weight": 0.8}, {"source": "staging-commands-008", "target": "batch-shadow-009", "type": "triggers", "weight": 0.42}, {"source": "staging-commands-008", "target": "core-firmware-006", "type": "calls", "weight": 0.96}, {"source": "batch-shadow-009", "target": "central-rules-engine-010", "type": "calls", "weight": 0.65}, {"source": "central-rules-engine-010", "target": "global-telemetry-011", "type": "triggers", "weight": 0.6}, {"source": "central-rules-engine-010", "target": "hot-shadow-015", "type": "queries", "weight": 0.63}, {"source": "central-rules-engine-010", "target": "batch-rules-engine-022", "type": "calls", "weight": 0.36}, {"source": "global-telemetry-011", "target": "cold-digital-twin-012", "type": "writes", "weight": 0.85}, {"source": "global-telemetry-011", "target": "central-rules-engine-010", "type": "reads", "weight": 0.33}, {"source": "global-telemetry-011", "target": "core-firmware-006", "type": "calls", "weight": 0.9}, {"source": "global-telemetry-011", "target": "shadow-kinesis-001", "type": "queries", "weight": 0.38}, {"source": "cold-digital-twin-012", "target": "primary-commands-013", "type": "writes", "weight": 0.94}, {"source": "primary-commands-013", "target": "core-firmware-014", "type": "reads", "weight": 0.63}, {"source": "primary-commands-013", "target": "global-telemetry-011", "type": "triggers", "weight": 0.97}, {"source": "core-firmware-014", "target": "hot-shadow-015", "type": "triggers", "weight": 0.76}, {"source": "core-firmware-014", "target": "batch-shadow-009", "type": "caches", "weight": 0.13}, {"source": "core-firmware-014", "target": "provisioning-lambda-002", "type": "triggers", "weight": 0.75}, {"source": "hot-shadow-015", "target": "edge-shadow-016", "type": "writes", "weight": 0.44}, {"source": "hot-shadow-015", "target": "central-rules-engine-010", "type": "triggers", "weight": 0.84}, {"source": "edge-shadow-016", "target": "realtime-fleet-017", "type": "caches", "weight": 0.69}, {"source": "edge-shadow-016", "target": "core-firmware-006", "type": "writes", "weight": 0.14}, {"source": "realtime-fleet-017", "target": "realtime-telemetry-018", "type": "caches", "weight": 0.95}, {"source": "realtime-telemetry-018", "target": "main-commands-019", "type": "subscribes", "weight": 0.37}, {"source": "realtime-telemetry-018", "target": "primary-commands-013", "type": "triggers", "weight": 0.24}, {"source": "realtime-telemetry-018", "target": "digital-twin-iot-000", "type": "reads", "weight": 0.48}, {"source": "main-commands-019", "target": "main-provisioning-020", "type": "queries", "weight": 0.85}, {"source": "main-commands-019", "target": "backup-digital-twin-005", "type": "writes", "weight": 0.98}, {"source": "main-commands-019", "target": "provisioning-lambda-002", "type": "caches", "weight": 0.63}, {"source": "main-provisioning-020", "target": "regional-firmware-021", "type": "queries", "weight": 0.58}, {"source": "regional-firmware-021", "target": "batch-rules-engine-022", "type": "subscribes", "weight": 0.62}, {"source": "regional-firmware-021", "target": "realtime-fleet-017", "type": "reads", "weight": 0.45}, {"source": "batch-rules-engine-022", "target": "central-firmware-023", "type": "calls", "weight": 0.9}, {"source": "batch-rules-engine-022", "target": "primary-commands-013", "type": "reads", "weight": 0.32}, {"source": "batch-rules-engine-022", "target": "regional-firmware-021", "type": "calls", "weight": 0.78}, {"source": "central-firmware-023", "target": "shadow-kinesis-001", "type": "queries", "weight": 0.47}], "metrics": {"total_services": 24, "total_dependencies": 52, "total_cost_monthly": 4021.7, "avg_degree": 4.33, "critical_nodes": ["core-firmware-006", "cold-telemetry-007", "central-rules-engine-010"], "cost_hotspots": ["main-commands-019", "batch-rules-engine-022", "staging-commands-008"], "is_dag": false, "density": 0.0942, "components": 1}}