{"nodes": [{"id": "moderation-alb-000", "name": "moderation-alb", "type": "load_balancer", "owner": "devops", "cost_monthly": 161.34, "cost_share": 7.08, "environment": "dr", "attributes": {"instance_type": "t3.medium", "auto_scaling": true, "multi_az": false, "encryption": false}, "color": "#14b8a6", "degree_centrality": 0.3077, "betweenness_centrality": 0.1667, "in_degree": 1, "out_degree": 3, "val": 13.231}, {"id": "notifications-eks-001", "name": "notifications-eks", "type": "service", "owner": "infra-core", "cost_monthly": 288.45, "cost_share": 12.65, "environment": "production", "attributes": {"instance_type": "m5.xlarge", "auto_scaling": true, "multi_az": false, "encryption": true}, "color": "#6366f1", "degree_centrality": 0.2308, "betweenness_centrality": 0.1795, "in_degree": 2, "out_degree": 1, "val": 10.924}, {"id": "moderation-aurora-002", "name": "moderation-aurora", "type": "database", "owner": "growth-eng", "cost_monthly": 241.47, "cost_share": 10.59, "environment": "production", "attributes": {"instance_type": "m5.xlarge", "auto_scaling": false, "multi_az": true, "encryption": true}, "color": "#10b981", "degree_centrality": 0.3077, "betweenness_centrality": 0.3269, "in_degree": 3, "out_degree": 1, "val": 13.231}, {"id": "reactions-elasticache-003", "name": "reactions-elasticache", "type": "cache", "owner": "infra-core", "cost_monthly": 178.39, "cost_share": 7.82, "environment": "production", "attributes": {"instance_type": "m5.large", "auto_scaling": true, "multi_az": false, "encryption": false}, "color": "#f59e0b", "degree_centrality": 0.2308, "betweenness_centrality": 0.3269, "in_degree": 1, "out_degree": 2, "val": 10.924}, {"id": "stories-cloudfront-004", "name": "stories-cloudfront", "type": "cdn", "owner": "api-gateway-team", "cost_monthly": 182.4, "cost_share": 8.0, "environment": "production", "attributes": {"instance_type": "t3.small", "auto_scaling": false, "multi_az": false, "encryption": true}, "color": "#f97316", "degree_centrality": 0.2308, "betweenness_centrality": 0.2244, "in_degree": 2, "out_degree": 1, "val": 10.924}, {"id": "main-messaging-005", "name": "main-messaging", "type": "storage", "owner": "search-team", "cost_monthly": 206.71, "cost_share": 9.06, "environment": "production", "attributes": {"instance_type": "t3.small", "auto_scaling": true, "multi_az": true, "encryption": true}, "color": "#3b82f6", "degree_centrality": 0.1538, "betweenness_centrality": 0.2244, "in_degree": 1, "out_degree": 1, "val": 8.614}, {"id": "public-follows-006", "name": "public-follows", "type": "service", "owner": "infra-core", "cost_monthly": 94.93, "cost_share": 4.16, "environment": "staging", "attributes": {"instance_type": "m5.large", "auto_scaling": false, "multi_az": true, "encryption": true}, "color": "#6366f1", "degree_centrality": 0.2308, "betweenness_centrality": 0.2244, "in_degree": 1, "out_degree": 2, "val": 10.924}, {"id": "primary-search-007", "name": "primary-search", "type": "serverless", "owner": "identity-team", "cost_monthly": 137.01, "cost_share": 6.01, "environment": "staging", "attributes": {"instance_type": "t3.medium", "auto_scaling": false, "multi_az": false, "encryption": true}, "color": "#8b5cf6", "degree_centrality": 0.2308, "betweenness_centrality": 0.1346, "in_degree": 1, "out_degree": 2, "val": 10.924}, {"id": "main-profiles-008", "name": "main-profiles", "type": "service", "owner": "content-team", "cost_monthly": 155.19, "cost_share": 6.81, "environment": "production", "attributes": {"instance_type": "c5.large", "auto_scaling": false, "multi_az": true, "encryption": true}, "color": "#6366f1", "degree_centrality": 0.3846, "betweenness_centrality": 0.3141, "in_degree": 2, "out_degree": 3, "val": 15.538}, {"id": "core-stories-009", "name": "core-stories", "type": "service", "owner": "frontend-guild", "cost_monthly": 22.49, "cost_share": 0.99, "environment": "staging", "attributes": {"instance_type": "t3.large", "auto_scaling": true, "multi_az": false, "encryption": false}, "color": "#6366f1", "degree_centrality": 0.2308, "betweenness_centrality": 0.0, "in_degree": 1, "out_degree": 2, "val": 10.924}, {"id": "public-stories-010", "name": "public-stories", "type": "database", "owner": "backend-squad", "cost_monthly": 194.29, "cost_share": 8.52, "environment": "production", "attributes": {"instance_type": "c5.large", "auto_scaling": true, "multi_az": false, "encryption": true}, "color": "#10b981", "degree_centrality": 0.4615, "betweenness_centrality": 0.1282, "in_degree": 5, "out_degree": 1, "val": 17.845}, {"id": "edge-stories-011", "name": "edge-stories", "type": "queue", "owner": "mobile-backend", "cost_monthly": 190.93, "cost_share": 8.37, "environment": "staging", "attributes": {"instance_type": "t3.micro", "auto_scaling": true, "multi_az": false, "encryption": true}, "color": "#ec4899", "degree_centrality": 0.1538, "betweenness_centrality": 0.1282, "in_degree": 1, "out_degree": 1, "val": 8.614}, {"id": "cold-follows-012", "name": "cold-follows", "type": "queue", "owner": "mobile-backend", "cost_monthly": 62.2, "cost_share": 2.73, "environment": "production", "attributes": {"instance_type": "t3.micro", "auto_scaling": false, "multi_az": true, "encryption": true}, "color": "#ec4899", "degree_centrality": 0.3077, "betweenness_centrality": 0.2756, "in_degree": 2, "out_degree": 2, "val": 13.231}, {"id": "realtime-media-upload-013", "name": "realtime-media-upload", "type": "search", "owner": "search-team", "cost_monthly": 164.59, "cost_share": 7.22, "environment": "dr", "attributes": {"instance_type": "t3.medium", "auto_scaling": false, "multi_az": false, "encryption": true}, "color": "#ef4444", "degree_centrality": 0.2308, "betweenness_centrality": 0.2436, "in_degree": 1, "out_degree": 2, "val": 10.924}], "links": [{"source": "moderation-alb-000", "target": "notifications-eks-001", "type": "triggers", "weight": 0.37}, {"source": "moderation-alb-000", "target": "public-stories-010", "type": "writes", "weight": 0.46}, {"source": "moderation-alb-000", "target": "cold-follows-012", "type": "caches", "weight": 0.17}, {"source": "notifications-eks-001", "target": "moderation-aurora-002", "type": "triggers", "weight": 0.7}, {"source": "moderation-aurora-002", "target": "reactions-elasticache-003", "type": "calls", "weight": 0.94}, {"source": "reactions-elasticache-003", "target": "stories-cloudfront-004", "type": "caches", "weight": 0.95}, {"source": "reactions-elasticache-003", "target": "main-profiles-008", "type": "calls", "weight": 0.39}, {"source": "stories-cloudfront-004", "target": "main-messaging-005", "type": "writes", "weight": 0.58}, {"source": "main-messaging-005", "target": "public-follows-006", "type": "triggers", "weight": 0.33}, {"source": "public-follows-006", "target": "primary-search-007", "type": "queries", "weight": 0.59}, {"source": "public-follows-006", "target": "public-stories-010", "type": "queries", "weight": 0.65}, {"source": "primary-search-007", "target": "main-profiles-008", "type": "calls", "weight": 0.99}, {"source": "primary-search-007", "target": "moderation-aurora-002", "type": "subscribes", "weight": 0.23}, {"source": "main-profiles-008", "target": "core-stories-009", "type": "queries", "weight": 0.4}, {"source": "main-profiles-008", "target": "public-stories-010", "type": "triggers", "weight": 0.24}, {"source": "main-profiles-008", "target": "moderation-alb-000", "type": "queries", "weight": 0.18}, {"source": "core-stories-009", "target": "public-stories-010", "type": "subscribes", "weight": 0.87}, {"source": "core-stories-009", "target": "moderation-aurora-002", "type": "queries", "weight": 0.94}, {"source": "public-stories-010", "target": "edge-stories-011", "type": "reads", "weight": 0.3}, {"source": "edge-stories-011", "target": "cold-follows-012", "type": "queries", "weight": 0.88}, {"source": "cold-follows-012", "target": "realtime-media-upload-013", "type": "queries", "weight": 0.72}, {"source": "cold-follows-012", "target": "public-stories-010", "type": "calls", "weight": 0.26}, {"source": "realtime-media-upload-013", "target": "notifications-eks-001", "type": "subscribes", "weight": 0.85}, {"source": "realtime-media-upload-013", "target": "stories-cloudfront-004", "type": "subscribes", "weight": 0.72}], "metrics": {"total_services": 14, "total_dependencies": 24, "total_cost_monthly": 2280.39, "avg_degree": 3.43, "critical_nodes": ["moderation-aurora-002", "reactions-elasticache-003", "main-profiles-008"], "cost_hotspots": ["notifications-eks-001", "moderation-aurora-002", "main-messaging-005"], "is_dag": false, "density": 0.1319, "components": 1}}